falcon_auth0/__init__.py
falcon_auth0/__http_factory/__init__.py
falcon_auth0/logger/__init__.py
falcon_auth0-1.0.9.dist-info/LICENSE.txt
falcon_auth0-1.0.9.dist-info/METADATA
falcon_auth0-1.0.9.dist-info/RECORD
falcon_auth0-1.0.9.dist-info/WHEEL
falcon_auth0-1.0.9.dist-info/top_level.txt
