Metadata-Version: 2.1
Name: falcon-auth0
Version: 1.0.9
Summary: Auth0 Authorization Middleware for The Falcon Web Framework
Home-page: https://github.com/mcculloh213/alchemist-stack
Author: H.D. "Chip" McCullough IV
Author-email: hdmccullough.work@gmail.com
License: MIT
Project-URL: Documentation, https://github.com/mcculloh213/falcon-auth0
Project-URL: Source, https://github.com/mcculloh213/falcon-auth0
Project-URL: Issue Tracker, https://github.com/mcculloh213/falcon-auth0/issues
Keywords: falcon auth0 authorization middleware
Platform: UNKNOWN
Classifier: Development Status :: 3 - Alpha
Classifier: Environment :: Plugins
Classifier: Intended Audience :: Developers
Classifier: License :: OSI Approved :: MIT License
Classifier: Natural Language :: English
Classifier: Programming Language :: Python :: 3
Classifier: Programming Language :: Python :: 3.5
Classifier: Programming Language :: Python :: 3.6
Classifier: Topic :: Internet :: WWW/HTTP :: WSGI :: Middleware
Classifier: Topic :: Software Development :: Libraries :: Application Frameworks
Classifier: Topic :: Software Development :: Libraries :: Python Modules
Requires-Python: >=3
Requires-Dist: falcon
Requires-Dist: pretend
Requires-Dist: python-jose-cryptodome
Requires-Dist: six
